gradio_highlightedcode/__init__.py
gradio_highlightedcode/highlightedcode.py
gradio_highlightedcode/highlightedcode.pyi
gradio_highlightedcode/templates/component/Index-COMtKkwP.js
gradio_highlightedcode/templates/component/dockerfile-CEE6bo6a.js
gradio_highlightedcode/templates/component/frontmatter-DeWKdYCf.js
gradio_highlightedcode/templates/component/index-B_0nvriU.js
gradio_highlightedcode/templates/component/index-Bh8J2SOT.js
gradio_highlightedcode/templates/component/index-C83s03OK.js
gradio_highlightedcode/templates/component/index-CrYb5Scy.js
gradio_highlightedcode/templates/component/index-CwvQZfH0.js
gradio_highlightedcode/templates/component/index-DRYwRkrj.js
gradio_highlightedcode/templates/component/index-eoOYcYY6.js
gradio_highlightedcode/templates/component/index.js
gradio_highlightedcode/templates/component/r-Bz1d3XP0.js
gradio_highlightedcode/templates/component/shell-C0C2sNA_.js
gradio_highlightedcode/templates/component/style.css
gradio_highlightedcode/templates/component/yaml-Dt6Tp2eU.js
gradio_highlightedcode/templates/example/index.js
gradio_highlightedcode/templates/example/style.css
gradio_highlightedcode-0.0.4.dist-info/METADATA
gradio_highlightedcode-0.0.4.dist-info/WHEEL
gradio_highlightedcode-0.0.4.dist-info/RECORD
